setup.py
wereurl.py
wereurl.egg-info/PKG-INFO
wereurl.egg-info/SOURCES.txt
wereurl.egg-info/dependency_links.txt
wereurl.egg-info/entry_points.txt
wereurl.egg-info/top_level.txt
wereurl.egg-info/zip-safe