Metadata-Version: 1.0
Name: wereurl
Version: 1
Summary: A module for detecting links in blobs of text.
Home-page: http://github.com/nickgartmann/wereurl/
Author: Nick Gartmann
Author-email: nick@rokkincat.com
License: BSD
Platform: any
Classifier: Intended Audience :: Developers
Classifier: License :: OSI Approved :: BSD License
Classifier: Operating System :: OS Independent
Classifier: Programming Language :: Python
